confboy/__init__.py
confboy-1.1.2.dist-info/LICENSE
confboy-1.1.2.dist-info/METADATA
confboy-1.1.2.dist-info/WHEEL
confboy-1.1.2.dist-info/top_level.txt
confboy-1.1.2.dist-info/RECORD
