Metadata-Version: 2.1
Name: confboy
Version: 1.1.2
Summary: Better configs with TOML support
Home-page: https://github.com/Euromance/confboy
Author: Euromancer
Author-email: kysput@gmail.com
License: UNKNOWN
Project-URL: Repository, https://github.com/Euromance/confboy
Platform: UNKNOWN
Classifier: Programming Language :: Python :: 3
Classifier: Programming Language :: Python :: 3.7
Classifier: Programming Language :: Python :: 3.8
Classifier: Programming Language :: Python :: 3.9
Classifier: License :: OSI Approved :: MIT License
Classifier: Operating System :: OS Independent
Requires-Python: >=3.7,<4.0
Requires-Dist: toml (==0.10.2)
Provides-Extra: dev
Requires-Dist: flake8 (==3.9.0) ; extra == 'dev'
Provides-Extra: test
Requires-Dist: pytest-cov (==2.11.1) ; extra == 'test'
Requires-Dist: pytest (==6.2.2) ; extra == 'test'
